font_check/__init__.py
font_check/module.py
font_check/data/data.txt
font_check-0.0.1.dist-info/METADATA
font_check-0.0.1.dist-info/WHEEL
font_check-0.0.1.dist-info/top_level.txt
font_check-0.0.1.dist-info/RECORD
