Metadata-Version: 2.4
Name: font_check
Version: 0.0.1
Home-page: https://github.com/SoyVitouPro/font_check
Author: soyvitou
Author-email: soyvitoupro@gmail.com
Classifier: Programming Language :: Python :: 3
Classifier: License :: OSI Approved :: MIT License
Classifier: Operating System :: OS Independent
Requires-Python: >=3.6
Requires-Dist: pillow
Dynamic: author
Dynamic: author-email
Dynamic: classifier
Dynamic: description
Dynamic: description-content-type
Dynamic: home-page
Dynamic: requires-dist
Dynamic: requires-python
